noFFT.cpython-313-darwin.so
nofft-0.0.1.dist-info/LICENSE
nofft-0.0.1.dist-info/METADATA
nofft-0.0.1.dist-info/WHEEL
nofft-0.0.1.dist-info/top_level.txt
nofft-0.0.1.dist-info/RECORD
