Metadata-Version: 2.2
Name: noFFT
Version: 0.0.1
Summary: A reference implementation of the Resonate algorithm in C++ for Python.
Home-page: https://github.com/alexandrefrancois/noFFT
Author: Alexandre R.J. Francois
Author-email: "Alexandre R.J. Francois" <alexandrefrancois@gmail.com>
License: Copyright (c) 2025 Alexandre R.J. Francois
Project-URL: Homepage, https://github.com/alexandrefrancois/noFFT
Project-URL: Issues, https://github.com/alexandrefrancois/noFFT/issues
Classifier: Programming Language :: Python :: 3
Classifier: Operating System :: MacOS
Requires-Python: >=3.8
License-File: LICENSE
Dynamic: author
Dynamic: home-page
Dynamic: requires-python
